cr_pre_commit_hooks/__init__.py
cr_pre_commit_hooks/docstrings.py
cr_pre_commit_hooks/py.typed
cr_pre_commit_hooks-0.1.1.dist-info/METADATA
cr_pre_commit_hooks-0.1.1.dist-info/WHEEL
cr_pre_commit_hooks-0.1.1.dist-info/entry_points.txt
cr_pre_commit_hooks-0.1.1.dist-info/RECORD
