Metadata-Version: 2.1
Name: cr-pre-commit-hooks
Version: 0.1.1
Summary: pre-commit hooks for ensuring consistency across our code base. Included are hooks which are not available elsewhere and also not super useful outside of a CR context.
Author: Mika Pflüger
Author-email: mika.pflueger@climate-resource.com
Requires-Python: >=3.9,<4.0
Classifier: Programming Language :: Python :: 3
Classifier: Programming Language :: Python :: 3.9
Classifier: Programming Language :: Python :: 3.10
Classifier: Programming Language :: Python :: 3.11
Requires-Dist: docstring-parser (>=0.15,<0.16)
